encpp/__init__.py
encpp/encpp.py
encpp-1.0.0.dist-info/METADATA
encpp-1.0.0.dist-info/WHEEL
encpp-1.0.0.dist-info/top_level.txt
encpp-1.0.0.dist-info/RECORD
